etimos/__init__.py
etimos/visualizer.py
etimos-0.1.dist-info/DESCRIPTION.rst
etimos-0.1.dist-info/METADATA
etimos-0.1.dist-info/RECORD
etimos-0.1.dist-info/WHEEL
etimos-0.1.dist-info/metadata.json
etimos-0.1.dist-info/top_level.txt
