Metadata-Version: 2.0
Name: etimos
Version: 0.1
Summary: Data Visualization Library
Home-page: https://github.com/Skopos-team/Etimos
Author: Skopos-team
Author-email: skopos.library@gmail.com
License: Apache2
Download-URL: https://github.com/Skopos-team/Etimos/archive/0.1.tar.gz
Keywords: testing,logging,example
Platform: UNKNOWN
Classifier: Programming Language :: Python :: 3.5
Classifier: Operating System :: POSIX
Classifier: Operating System :: Unix
Classifier: Operating System :: MacOS
